README.md
setup.py
tremendous_theme_selector/__init__.py
tremendous_theme_selector/__main__.py
tremendous_theme_selector/utils.py
tremendous_theme_selector.egg-info/PKG-INFO
tremendous_theme_selector.egg-info/SOURCES.txt
tremendous_theme_selector.egg-info/dependency_links.txt
tremendous_theme_selector.egg-info/requires.txt
tremendous_theme_selector.egg-info/top_level.txt