Metadata-Version: 2.1
Name: tremendous-theme-selector
Version: 0.93
Summary: A simple app for manually annotating audio files
Home-page: https://github.com/zeionara/tremednous-theme-selector
Author: zeionara
Author-email: zeionara@gmail.com
License: UNKNOWN
Platform: UNKNOWN
Classifier: Programming Language :: Python :: 3
Classifier: License :: OSI Approved :: MIT License
Classifier: Operating System :: OS Independent
